lilyponddist/__init__.py
lilyponddist-1.2.1.dist-info/licenses/LICENSE
lilyponddist-1.2.1.dist-info/METADATA
lilyponddist-1.2.1.dist-info/WHEEL
lilyponddist-1.2.1.dist-info/top_level.txt
lilyponddist-1.2.1.dist-info/RECORD
