Metadata-Version: 2.4
Name: lilyponddist
Version: 1.2.1
Summary: lilypond distribution as a python package
Author-email: Eduardo Moguillansky <eduardo.moguillansky@gmail.com>
License: GNU LilyPond is free software: you can redistribute it and/or modify
Project-URL: Homepage, https://github.com/gesellkammer/lilyponddist
Classifier: Programming Language :: Python :: 3
Classifier: Operating System :: OS Independent
Requires-Python: >=3.10
License-File: LICENSE
Requires-Dist: appdirs
Requires-Dist: progressbar
Dynamic: license-file
